{
  "douyin_vHan09233": {
    "platform": "douyin",
    "id": "vHan09233",
    "name": "韩冰",
    "sec_uid": "MS4wLjABAAAAUXBNFnWLvl9T8ylgAbD1auR_o5FL3dF7ic0KMYN9_88",
    "avatar": "https://p11.douyinpic.com/aweme/100x100/aweme-avatar/tos-cn-avt-0015_e6bc88d850b3dd8b33830f8a7ecfeab4.jpeg?from=3067671334",
    "latest_post": {
      "id": "7662278718006384731",
      "platform": "douyin",
      "name": "韩冰",
      "title": "惡魔未必有我坏ᝯ◂ᗜ𐋣ᗜ▾ಎ↝",
      "views": 0,
      "likes": 94465,
      "cover": "https://p5-ex-gddgtc-sign.douyinpic.com/tos-cn-i-0813c001/okBulJIAa9ALCI8wCS7AhqefAPG7BEAQSAeU8r~tplv-dy-cropcenter:300:400.png?lk3s=2aa63f9f&x-expires=1784109600&x-signature=KRzN%2F3GKu7Ke5ouzucuAmGylnm0%3D&from=715538335&s=PackSourceEnum_DOUYIN_REFLOW&se=true&sh=300_400&sc=cover&biz_tag=aweme_video&l=20260715122609259CE109A6D253612F62",
      "avatar": "https://p11.douyinpic.com/aweme/100x100/aweme-avatar/tos-cn-avt-0015_e6bc88d850b3dd8b33830f8a7ecfeab4.jpeg?from=3067671334",
      "url": "https://www.douyin.com/video/7662278718006384731",
      "time": "2026-07-15T04:29:52.896742",
      "sort_key": 7662278718006384731
    },
    "total_seen": 24,
    "new_count": 0,
    "last_check": "2026-07-15T04:26:01.527404",
    "status": "ok"
  },
  "douyin_FengBro": {
    "platform": "douyin",
    "id": "FengBro",
    "name": "峰哥亡命天涯",
    "sec_uid": "MS4wLjABAAAAXrcPvX8QchAY5irWMAxU379DgfCBEOoztZoCcOUqi8I",
    "avatar": "https://p11.douyinpic.com/aweme/100x100/aweme-avatar/mosaic-legacy_2d6f0000113c4daec8515.jpeg?from=3067671334",
    "latest_post": {
      "id": "7660491790876851825",
      "platform": "douyin",
      "name": "峰哥亡命天涯",
      "title": "峰哥在受首尔品尝韩牛烤肉 #韩国吃什么 #韩国美食推荐 #韩国特色美食",
      "views": 0,
      "likes": 81064,
      "cover": "https://p5-ex-gddgtc-sign.douyinpic.com/tos-cn-i-0813c000-ce/owLAEJsnWIAedAFPXiiIPPACHwi3KCBB1EceAi~tplv-dy-cropcenter:300:400.png?lk3s=2aa63f9f&x-expires=1784109600&x-signature=imI1v3%2BfzvLLdb2X1s0i7oGFlf8%3D&from=715538335&s=PackSourceEnum_DOUYIN_REFLOW&se=true&sh=300_400&sc=cover&biz_tag=aweme_video&l=2026071512295839D37DBE43B8674E3F92",
      "avatar": "https://p11.douyinpic.com/aweme/100x100/aweme-avatar/mosaic-legacy_2d6f0000113c4daec8515.jpeg?from=3067671334",
      "url": "https://www.douyin.com/video/7660491790876851825",
      "time": "2026-07-15T04:33:41.348403",
      "sort_key": 7660491790876851825
    },
    "total_seen": 20,
    "new_count": 0,
    "last_check": "2026-07-15T04:26:01.527404",
    "status": "ok"
  },
  "douyin_llqq192": {
    "platform": "douyin",
    "id": "llqq192",
    "name": "栗子鸡",
    "sec_uid": "MS4wLjABAAAAPBP113is5zbadFY77J3HQRZ72SDrhQZC3m6qQcOY5f0sI4M0suqH5QrUQKM3_iWi",
    "avatar": "https://p26.douyinpic.com/aweme/100x100/aweme-avatar/tos-cn-i-0813c001_oAzuB7B8IAH6CQQAEvAwiAAXAeiF9DfB3giBgi.jpeg?from=3067671334",
    "latest_post": {
      "id": "7658638889217224691",
      "platform": "douyin",
      "name": "栗子鸡",
      "title": "我做這麼多只是為了沒有眼淚的明天",
      "views": 0,
      "likes": 273,
      "cover": "https://p3-sign.douyinpic.com/tos-cn-i-0813/oAxIueh7CG5IRIiR4uLCAbQI2Ae7A6veDAIpAe~tplv-dy-cropcenter:300:400.png?lk3s=2aa63f9f&x-expires=1784109600&x-signature=9kEGdnG9e4kfhSsNN%2B4aqXKeYlM%3D&from=715538335&s=PackSourceEnum_DOUYIN_REFLOW&se=true&sh=300_400&sc=cover&biz_tag=aweme_video&l=202607151233466D2ED4CD4B5B0063E716",
      "avatar": "https://p26.douyinpic.com/aweme/100x100/aweme-avatar/tos-cn-i-0813c001_oAzuB7B8IAH6CQQAEvAwiAAXAeiF9DfB3giBgi.jpeg?from=3067671334",
      "url": "https://www.douyin.com/note/7658638889217224691",
      "time": "2026-07-15T04:37:33.851131",
      "sort_key": 7658638889217224691
    },
    "total_seen": 18,
    "new_count": 0,
    "last_check": "2026-07-15T04:26:01.527404",
    "status": "ok"
  },
  "douyin_83134194400": {
    "platform": "douyin",
    "id": "83134194400",
    "name": "27～",
    "sec_uid": "MS4wLjABAAAAPzcJluI9HAtkdShRBONh_jw9miEsJ1d6Tvzw4BbOdMTFqivBlDEtRgAeEBHn6lNO",
    "avatar": "https://p26.douyinpic.com/aweme/100x100/aweme-avatar/tos-cn-avt-0015_7dc1ff2e4510f2f81984a83693591b0f.jpeg?from=3067671334",
    "latest_post": {
      "id": "7661633491398949498",
      "platform": "douyin",
      "name": "27～",
      "title": "跟BGM极度适配！#露宿街头的人 #睡马路的人 #席地而睡 #睡大街 #打工人打地铺",
      "views": 0,
      "likes": 765,
      "cover": "https://p3-sign.douyinpic.com/tos-cn-i-0813c000-ce/ocAATFwnbUXuDlaA9fEC5cAewoEiEBAIgqJnES~tplv-dy-cropcenter:300:400.png?lk3s=2aa63f9f&x-expires=1784109600&x-signature=sOPh2omxje%2B%2BdEbXw%2FNo2gUwCtA%3D&from=715538335&s=PackSourceEnum_DOUYIN_REFLOW&se=true&sh=300_400&sc=cover&biz_tag=aweme_video&l=20260715123738643159F9DA487A648911",
      "avatar": "https://p26.douyinpic.com/aweme/100x100/aweme-avatar/tos-cn-avt-0015_7dc1ff2e4510f2f81984a83693591b0f.jpeg?from=3067671334",
      "url": "https://www.douyin.com/note/7661633491398949498",
      "time": "2026-07-15T04:41:47.639237",
      "sort_key": 7661633491398949498
    },
    "total_seen": 16,
    "new_count": 0,
    "last_check": "2026-07-15T04:26:01.527404",
    "status": "ok"
  },
  "douyin_JACROX001": {
    "platform": "douyin",
    "id": "JACROX001",
    "name": "薛大兵",
    "sec_uid": "MS4wLjABAAAA51MXSVWRp-26G0czUV08_9PuP91qIxqXoaHs9NspFk9PTalY3FW5XqjhPsjNpviN",
    "avatar": "https://p11.douyinpic.com/aweme/100x100/aweme-avatar/tos-cn-avt-0015_7c4af679ce501c560bf231949784f7ab.jpeg?from=3067671334",
    "latest_post": {
      "id": "7662375755725029349",
      "platform": "douyin",
      "name": "薛大兵",
      "title": "我敢断言，奥总必成功 #薛大兵 #创业 #ORR",
      "views": 0,
      "likes": 503,
      "cover": "https://p11-sign.douyinpic.com/tos-cn-p-0015c000-ce/okAeEAiqeEWCt9LQkSWfCFOVNDqYKjI09jbUnw~tplv-dy-cropcenter:300:400.png?lk3s=2aa63f9f&x-expires=1784109600&x-signature=8hPF4ccKpsn9y8xkJ2FJ1dRxV7Y%3D&from=715538335&s=PackSourceEnum_DOUYIN_REFLOW&se=true&sh=300_400&sc=cover&biz_tag=aweme_video&l=202607151241524D8C93A166111A5F811C",
      "avatar": "https://p11.douyinpic.com/aweme/100x100/aweme-avatar/tos-cn-avt-0015_7c4af679ce501c560bf231949784f7ab.jpeg?from=3067671334",
      "url": "https://www.douyin.com/video/7662375755725029349",
      "time": "2026-07-15T04:45:40.839900",
      "sort_key": 7662375755725029349
    },
    "total_seen": 16,
    "new_count": 0,
    "last_check": "2026-07-15T04:26:01.527404",
    "status": "ok"
  }
}